fake_py_pathy_storage-0.1.6.dist-info/licenses/LICENSE
fakepy/pathy_storage/__init__.py
fakepy/pathy_storage/aws_s3.py
fakepy/pathy_storage/azure_cloud_storage.py
fakepy/pathy_storage/cloud.py
fakepy/pathy_storage/google_cloud_storage.py
fakepy/pathy_storage/helpers.py
fakepy/pathy_storage/tests/__init__.py
fakepy/pathy_storage/tests/data.py
fakepy/pathy_storage/tests/test_storages.py
fake_py_pathy_storage-0.1.6.dist-info/METADATA
fake_py_pathy_storage-0.1.6.dist-info/WHEEL
fake_py_pathy_storage-0.1.6.dist-info/top_level.txt
fake_py_pathy_storage-0.1.6.dist-info/RECORD
