Metadata-Version: 2.4
Name: fake-py-pathy-storage
Version: 0.1.6
Summary: Pathy storage for fake.py
Author-email: Artur Barseghyan <artur.barseghyan@gmail.com>
Maintainer-email: Artur Barseghyan <artur.barseghyan@gmail.com>
License-Expression: MIT
Project-URL: Homepage, https://github.com/barseghyanartur/fake-py-pathy-storage/
Project-URL: Issues, https://github.com/barseghyanartur/fake-py-pathy-storage/issues
Project-URL: Documentation, https://fake-py-pathy-storage.readthedocs.io/
Project-URL: Repository, https://github.com/barseghyanartur/fake-py-pathy-storage/
Project-URL: Changelog, https://fake-py-pathy-storage.readthedocs.io/en/latest/changelog.html
Keywords: fake data,test data
Classifier: Development Status :: 4 - Beta
Classifier: Intended Audience :: Developers
Classifier: Operating System :: OS Independent
Classifier: Programming Language :: Python :: 3
Classifier: Programming Language :: Python :: 3.10
Classifier: Programming Language :: Python :: 3.11
Classifier: Programming Language :: Python :: 3.12
Classifier: Programming Language :: Python :: 3.13
Classifier: Programming Language :: Python :: 3.9
Classifier: Programming Language :: Python
Classifier: Topic :: Software Development :: Testing
Classifier: Topic :: Software Development
License-File: LICENSE
Requires-Dist: fake.py>=0.9.5
Requires-Dist: pathy<0.12.0,>=0.10.0
Provides-Extra: all
Requires-Dist: fake-py-pathy-storage[azure,dev,docs,gcs,s3,test]; extra == "all"
Provides-Extra: dev
Requires-Dist: black; extra == "dev"
Requires-Dist: build; extra == "dev"
Requires-Dist: detect-secrets; extra == "dev"
Requires-Dist: doc8; extra == "dev"
Requires-Dist: ipython; extra == "dev"
Requires-Dist: isort; extra == "dev"
Requires-Dist: mypy; extra == "dev"
Requires-Dist: pip-tools; extra == "dev"
Requires-Dist: pydoclint; extra == "dev"
Requires-Dist: ruff; extra == "dev"
Requires-Dist: twine; extra == "dev"
Requires-Dist: uv; extra == "dev"
Requires-Dist: wheel; extra == "dev"
Provides-Extra: test
Requires-Dist: django; extra == "test"
Requires-Dist: moto[s3]; extra == "test"
Requires-Dist: parametrize; extra == "test"
Requires-Dist: pytest; extra == "test"
Requires-Dist: pytest-codeblock; extra == "test"
Requires-Dist: pytest-cov; extra == "test"
Requires-Dist: pytest-django; extra == "test"
Provides-Extra: docs
Requires-Dist: sphinx<6.0; extra == "docs"
Requires-Dist: sphinx-rtd-theme>=1.3.0; extra == "docs"
Requires-Dist: sphinx-no-pragma; extra == "docs"
Provides-Extra: gcs
Requires-Dist: pathy[gcs]<0.12.0,>=0.10.0; extra == "gcs"
Provides-Extra: s3
Requires-Dist: pathy[s3]<0.12.0,>=0.10.0; extra == "s3"
Provides-Extra: azure
Requires-Dist: pathy[azure]<0.12.0,>=0.10.0; extra == "azure"
Dynamic: license-file
